airadar/__init__.py
airadar/_version.py
airadar/api/__init__.py
airadar/api/api_client.py
airadar/extractors/__init__.py
airadar/extractors/dependency.py
airadar/radar.py
airadar/tools/__init__.py
airadar/tools/cloud_storage.py
airadar/tools/model_registry.py
airadar/tracking/__init__.py
airadar/tracking/decorators.py
airadar/tracking/fluent.py
airadar/tracking/mlflow.py
airadar/tracking/model.py
airadar/tracking/plugins/__init__.py
airadar/tracking/plugins/mlflow/__init__.py
airadar/tracking/plugins/mlflow/run_context_provider.py
airadar/typing/__init__.py
airadar/typing/types_utils.py
airadar/utils/__init__.py
airadar/utils/auth.py
airadar/utils/base_model.py
airadar/utils/config.py
airadar-0.10.0.dist-info/METADATA
airadar-0.10.0.dist-info/WHEEL
airadar-0.10.0.dist-info/entry_points.txt
airadar-0.10.0.dist-info/RECORD
