Metadata-Version: 2.3
Name: airadar
Version: 0.10.0
Summary: Radar sdk
Author: ProtectAI
Author-email: community@protectai.com
Requires-Python: >=3.10,<3.13
Classifier: Programming Language :: Python :: 3
Classifier: Programming Language :: Python :: 3.10
Classifier: Programming Language :: Python :: 3.11
Classifier: Programming Language :: Python :: 3.12
Requires-Dist: GitPython (>=3.1.41,<4.0.0)
Requires-Dist: cryptography (>=44.0.1,<46.0.0)
Requires-Dist: docstring-parser (==0.16)
Requires-Dist: google-cloud-storage (>=2.19.0,<3.0.0)
Requires-Dist: pydantic (>=2.0.0)
Requires-Dist: pyjwt (>=2.9.0,<3.0.0)
Requires-Dist: python-dotenv (>=1.0.0,<2.0.0)
Requires-Dist: requests (>=2.32.3,<3.0.0)
Requires-Dist: typing_extensions (>=4.0.0,<5.0.0)
